nmk/__init__.py
nmk/__main__.py
nmk/envbackend.py
nmk/errors.py
nmk/logs.py
nmk/utils.py
nmk/_internal/__init__.py
nmk/_internal/build.py
nmk/_internal/cache.py
nmk/_internal/completion.py
nmk/_internal/envbackend_legacy.py
nmk/_internal/files.py
nmk/_internal/loader.py
nmk/_internal/model.yml
nmk/_internal/parser.py
nmk/model/__init__.py
nmk/model/builder.py
nmk/model/config.py
nmk/model/internal.yml
nmk/model/keys.py
nmk/model/model.py
nmk/model/resolver.py
nmk/model/task.py
nmk/tests/__init__.py
nmk/tests/tester.py
nmk-1.4.3.dist-info/licenses/LICENSE
nmk-1.4.3.dist-info/METADATA
nmk-1.4.3.dist-info/WHEEL
nmk-1.4.3.dist-info/entry_points.txt
nmk-1.4.3.dist-info/top_level.txt
nmk-1.4.3.dist-info/RECORD
