Metadata-Version: 2.4
Name: nmk
Version: 1.4.3
Summary: Next-gen make-like build system
Author: The dynod project
Maintainer: The dynod project
License: MIT License
Project-URL: Homepage, https://github.com/dynod/nmk
Project-URL: Repository, https://github.com/dynod/nmk
Project-URL: Issues, https://github.com/dynod/nmk/issues?q=is%3Aopen+is%3Aissue
Classifier: Programming Language :: Python :: 3.10
Classifier: Programming Language :: Python :: 3.11
Classifier: Programming Language :: Python :: 3.12
Classifier: Programming Language :: Python :: 3.13
Classifier: Programming Language :: Python :: 3.14
Requires-Python: >=3.10
License-File: LICENSE
Requires-Dist: argcomplete
Requires-Dist: coloredlogs
Requires-Dist: pyyaml
Requires-Dist: jsonschema
Requires-Dist: rich
Requires-Dist: requests
Requires-Dist: buildenv
Dynamic: license-file
